mindify/__init__.py
mindify/text.py
mindify/utils.py
mindify/audio/__init__.py
mindify/audio/loss/__init__.py
mindify/audio/nn/__init__.py
mindify/audio/nn/modules/__init__.py
mindify/backup/__init__.py
mindify/backup/database/__init__.py
mindify/backup/database/pdo.py
mindify/backup/datasets/__init__.py
mindify/backup/datasets/image_seg_dataset.py
mindify/backup/datasets/kaggle/__init__.py
mindify/backup/datasets/kaggle/tgs_salt_identification_challenge.py
mindify/backup/datasets/kaggle/utils.py
mindify/backup/helpers/__init__.py
mindify/backup/helpers/data_helper.py
mindify/backup/helpers/date_helper.py
mindify/backup/helpers/dict_object.py
mindify/backup/helpers/file_helper.py
mindify/backup/helpers/object_helper.py
mindify/backup/helpers/text_helper.py
mindify/backup/kaggle/__init__.py
mindify/backup/kaggle/kaggle_api.py
mindify/backup/ml/__init__.py
mindify/backup/ml/common.py
mindify/backup/nlp/__init__.py
mindify/backup/nlp/alphabet.py
mindify/backup/pytorch_lightning/__init__.py
mindify/backup/pytorch_lightning/hparams.py
mindify/backup/pytorch_lightning/progressbar.py
mindify/backup/pytorch_lightning/trainer.py
mindify/backup/vision/__init__.py
mindify/backup/vision/net_module.py
mindify/backup/vision/net_tunner.py
mindify/backup/vision/datasets/__init__.py
mindify/backup/vision/datasets/cifar.py
mindify/backup/vision/datasets/common.py
mindify/backup/vision/datasets/imagenet.py
mindify/backup/vision/datasets/mnist.py
mindify/backup/vision/modules/__init__.py
mindify/backup/vision/modules/base.py
mindify/backup/vision/modules/cbam.py
mindify/backup/vision/modules/efficientnet.py
mindify/backup/vision/modules/inception_v3.py
mindify/backup/vision/modules/inception_v4.py
mindify/backup/vision/modules/mobilenet.py
mindify/backup/vision/modules/resnet.py
mindify/base/__init__.py
mindify/base/dict_object.py
mindify/cache/__init__.py
mindify/cache/cache.py
mindify/cache/core.py
mindify/cache/oss_client.py
mindify/data/__init__.py
mindify/data/transformers.py
mindify-0.1.0.dist-info/METADATA
mindify-0.1.0.dist-info/WHEEL
mindify-0.1.0.dist-info/top_level.txt
mindify-0.1.0.dist-info/RECORD
